{"Rings":[{"BlockStart":"8:30 am","Judge":"DR BOB G SMITH (107)","Number":1,"Count":4,"ClassName":"Open Senior","CountAhead":0},{"BlockStart":"8:30 am","Judge":"DR BOB G SMITH (107)","Number":1,"Count":10,"ClassName":"Open Intermediate","CountAhead":4},{"BlockStart":"8:30 am","Judge":"DR BOB G SMITH (107)","Number":1,"Count":5,"ClassName":"Open Junior","CountAhead":14},{"BlockStart":"8:30 am","Judge":"DR BOB G SMITH (107)","Number":1,"Count":2,"ClassName":"Novice Intermediate","CountAhead":19},{"BlockStart":"8:30 am","Judge":"DR BOB G SMITH (107)","Number":1,"Count":2,"ClassName":"Novice Junior","CountAhead":21},{"BlockStart":"9:40 am","Judge":"DR BOB G SMITH (107)","Number":1,"Count":6,"BreedName":"Retrievers (Labrador) ","DogCount":2,"BitchCount":1,"SpecialDogCount":2,"SpecialBitchCount":0,"CountAhead":0},{"BlockStart":"9:40 am","Judge":"DR BOB G SMITH (107)","Number":1,"Count":1,"IsVeteran":true,"BreedName":"Retrievers (Labrador) ","CountAhead":6},{"BlockStart":"9:40 am","Judge":"DR BOB G SMITH (107)","Number":1,"Count":9,"BreedName":"Weimaraners ","DogCount":3,"BitchCount":4,"SpecialDogCount":0,"SpecialBitchCount":2,"CountAhead":7},{"BlockStart":"9:40 am","Judge":"DR BOB G SMITH (107)","Number":1,"Count":4,"BreedName":"Spinoni Italiani ","DogCount":1,"BitchCount":0,"SpecialDogCount":1,"SpecialBitchCount":2,"CountAhead":16},{"BlockStart":"9:40 am","Judge":"DR BOB G SMITH (107)","Number":1,"Count":7,"BreedName":"Spaniels (Welsh Springer) ","DogCount":0,"BitchCount":2,"SpecialDogCount":2,"SpecialBitchCount":2,"CountAhead":20},{"BlockStart":"9:40 am","Judge":"DR BOB G SMITH (107)","Number":1,"Count":1,"IsVeteran":true,"BreedName":"Spaniels (Welsh Springer) ","CountAhead":27},{"BlockStart":"10:40 am","Judge":"DR BOB G SMITH (107)","Number":1,"Count":2,"BreedName":"Retrievers (Curly-Coated) ","DogCount":0,"BitchCount":1,"SpecialDogCount":0,"SpecialBitchCount":0,"CountAhead":0},{"BlockStart":"10:40 am","Judge":"DR BOB G SMITH (107)","Number":1,"Count":1,"IsVeteran":true,"BreedName":"Retrievers (Curly-Coated) ","CountAhead":2},{"BlockStart":"10:40 am","Judge":"DR BOB G SMITH (107)","Number":1,"Count":2,"BreedName":"Spaniels (American Water) ","DogCount":2,"BitchCount":0,"SpecialDogCount":0,"SpecialBitchCount":0,"CountAhead":3},{"BlockStart":"10:40 am","Judge":"DR BOB G SMITH (107)","Number":1,"Count":8,"BreedName":"Spaniels (Irish Water) ","DogCount":2,"BitchCount":5,"SpecialDogCount":1,"SpecialBitchCount":0,"CountAhead":5},{"BlockStart":"10:40 am","Judge":"DR BOB G SMITH (107)","Number":1,"Count":2,"BreedName":"Spaniels (English Springer) ","DogCount":1,"BitchCount":0,"SpecialDogCount":0,"SpecialBitchCount":1,"CountAhead":13},{"BlockStart":"10:40 am","Judge":"DR BOB G SMITH (107)","Number":1,"Count":10,"BreedName":"Retrievers (Golden) ","DogCount":6,"BitchCount":2,"SpecialDogCount":1,"SpecialBitchCount":1,"CountAhead":15},{"BlockStart":"11:45 am","Judge":"MS JOANNE M BUEHLER (6)","Number":1,"Count":5,"BreedName":"Dachshunds (Smooth) ","DogCount":2,"BitchCount":2,"SpecialDogCount":0,"SpecialBitchCount":1,"CountAhead":0},{"BlockStart":"11:45 am","Judge":"MS JOANNE M BUEHLER (6)","Number":1,"Count":1,"BreedName":"Dachshunds (Wirehaired) ","DogCount":1,"BitchCount":0,"SpecialDogCount":0,"SpecialBitchCount":0,"CountAhead":5},{"BlockStart":"12:25 pm","Judge":"DR BOB G SMITH\n","Number":1,"Count":4,"BreedName":"Spaniels (Cocker) Ascob","DogCount":0,"BitchCount":3,"SpecialDogCount":1,"SpecialBitchCount":0,"CountAhead":0},{"BlockStart":"12:25 pm","Judge":"DR BOB G SMITH\n","Number":1,"Count":10,"BreedName":"Spaniels (English Cocker) ","DogCount":4,"BitchCount":5,"SpecialDogCount":0,"SpecialBitchCount":1,"CountAhead":4},{"BlockStart":"12:25 pm","Judge":"DR BOB G SMITH\n","Number":1,"Count":2,"BreedName":"Spaniels (Cocker) Black","DogCount":0,"BitchCount":1,"SpecialDogCount":1,"SpecialBitchCount":0,"CountAhead":14},{"BlockStart":"12:25 pm","Judge":"DR BOB G SMITH\n","Number":1,"Count":12,"BreedName":"Retrievers (Nova Scotia Duck Tolling) ","DogCount":3,"BitchCount":6,"SpecialDogCount":1,"SpecialBitchCount":2,"CountAhead":16},{"BlockStart":"12:25 pm","Judge":"DR BOB G SMITH\n","Number":1,"Count":1,"BreedName":"Retrievers (Flat-Coated) ","DogCount":0,"BitchCount":0,"SpecialDogCount":1,"SpecialBitchCount":0,"CountAhead":28},{"BlockStart":"12:25 pm","Judge":"DR BOB G SMITH\n","Number":1,"Count":1,"BreedName":"Spaniels (Clumber) ","DogCount":0,"BitchCount":0,"SpecialDogCount":1,"SpecialBitchCount":0,"CountAhead":29},{"BlockStart":"12:25 pm","Judge":"DR BOB G SMITH\n","Number":1,"Count":4,"BreedName":"Spaniels (Cocker) Parti-Color","DogCount":0,"BitchCount":2,"SpecialDogCount":1,"SpecialBitchCount":1,"CountAhead":30},{"BlockStart":"8:30 am","Judge":"MRS RITA J RYNDER (106)","Number":2,"Count":2,"BreedName":"Bullmastiffs ","DogCount":0,"BitchCount":1,"SpecialDogCount":0,"SpecialBitchCount":1,"CountAhead":0},{"BlockStart":"8:30 am","Judge":"MRS RITA J RYNDER (106)","Number":2,"Count":11,"BreedName":"Doberman Pinschers ","DogCount":4,"BitchCount":3,"SpecialDogCount":3,"SpecialBitchCount":1,"CountAhead":2},{"BlockStart":"8:30 am","Judge":"MRS RITA J RYNDER (106)","Number":2,"Count":14,"BreedName":"Great Danes ","DogCount":2,"BitchCount":7,"SpecialDogCount":4,"SpecialBitchCount":1,"CountAhead":13},{"BlockStart":"9:35 am","Judge":"MRS RITA J RYNDER (106)","Number":2,"Count":5,"BreedName":"Rottweilers ","DogCount":1,"BitchCount":2,"SpecialDogCount":2,"SpecialBitchCount":0,"CountAhead":0},{"BlockStart":"9:35 am","Judge":"MRS RITA J RYNDER (106)","Number":2,"Count":16,"BreedName":"Boxers ","DogCount":8,"BitchCount":6,"SpecialDogCount":0,"SpecialBitchCount":2,"CountAhead":5},{"BlockStart":"9:35 am","Judge":"MRS RITA J RYNDER (106)","Number":2,"Count":14,"BreedName":"Newfoundlands ","DogCount":7,"BitchCount":3,"SpecialDogCount":1,"SpecialBitchCount":3,"CountAhead":21},{"BlockStart":"11:00 am","Judge":"MRS RITA J RYNDER (106)","Number":2,"Count":2,"BreedName":"Akitas ","DogCount":0,"BitchCount":1,"SpecialDogCount":0,"SpecialBitchCount":0,"CountAhead":0},{"BlockStart":"11:00 am","Judge":"MRS RITA J RYNDER (106)","Number":2,"Count":1,"IsVeteran":true,"BreedName":"Akitas ","CountAhead":2},{"BlockStart":"11:00 am","Judge":"MRS RITA J RYNDER (106)","Number":2,"Count":4,"BreedName":"Siberian Huskies ","DogCount":1,"BitchCount":1,"SpecialDogCount":1,"SpecialBitchCount":1,"CountAhead":3},{"BlockStart":"11:00 am","Judge":"MRS RITA J RYNDER (106)","Number":2,"Count":6,"BreedName":"Bernese Mountain Dogs ","DogCount":1,"BitchCount":2,"SpecialDogCount":3,"SpecialBitchCount":0,"CountAhead":7},{"BlockStart":"11:00 am","Judge":"MRS RITA J RYNDER (106)","Number":2,"Count":12,"BreedName":"Standard Schnauzers ","DogCount":5,"BitchCount":2,"SpecialDogCount":3,"SpecialBitchCount":2,"CountAhead":13},{"BlockStart":"11:00 am","Judge":"MRS RITA J RYNDER (106)","Number":2,"Count":9,"BreedName":"Samoyeds ","DogCount":2,"BitchCount":5,"SpecialDogCount":0,"SpecialBitchCount":2,"CountAhead":25},{"BlockStart":"12:20 pm","Judge":"MRS RITA J RYNDER (106)","Number":2,"Count":6,"BreedName":"Giant Schnauzers ","DogCount":0,"BitchCount":5,"SpecialDogCount":1,"SpecialBitchCount":0,"CountAhead":0},{"BlockStart":"12:20 pm","Judge":"MRS RITA J RYNDER (106)","Number":2,"Count":1,"BreedName":"German Pinschers ","DogCount":0,"BitchCount":0,"SpecialDogCount":1,"SpecialBitchCount":0,"CountAhead":6},{"BlockStart":"12:20 pm","Judge":"MRS RITA J RYNDER (106)","Number":2,"Count":1,"BreedName":"Alaskan Malamutes ","DogCount":0,"BitchCount":0,"SpecialDogCount":0,"SpecialBitchCount":1,"CountAhead":7},{"BlockStart":"12:20 pm","Judge":"MRS RITA J RYNDER (106)","Number":2,"Count":1,"BreedName":"Great Pyrenees ","DogCount":0,"BitchCount":0,"SpecialDogCount":1,"SpecialBitchCount":0,"CountAhead":8},{"BlockStart":"12:20 pm","Judge":"MRS RITA J RYNDER (106)","Number":2,"Count":1,"BreedName":"Portuguese Water Dogs ","DogCount":0,"BitchCount":1,"SpecialDogCount":0,"SpecialBitchCount":0,"CountAhead":9},{"BlockStart":"12:20 pm","Judge":"MRS RITA J RYNDER (106)","Number":2,"Count":1,"BreedName":"Tibetan Mastiffs ","DogCount":0,"BitchCount":1,"SpecialDogCount":0,"SpecialBitchCount":0,"CountAhead":10},{"BlockStart":"12:50 pm","Judge":"MRS PAULA HARTINGER (44)","Number":2,"Count":6,"BreedName":"Basset Hounds ","DogCount":1,"BitchCount":3,"SpecialDogCount":1,"SpecialBitchCount":1,"CountAhead":0},{"BlockStart":"12:50 pm","Judge":"MRS PAULA HARTINGER (44)","Number":2,"Count":9,"BreedName":"Whippets ","DogCount":3,"BitchCount":2,"SpecialDogCount":3,"SpecialBitchCount":1,"CountAhead":6},{"BlockStart":"12:50 pm","Judge":"MRS PAULA HARTINGER (44)","Number":2,"Count":3,"BreedName":"Scottish Deerhounds ","DogCount":2,"BitchCount":1,"SpecialDogCount":0,"SpecialBitchCount":0,"CountAhead":15},{"BlockStart":"12:50 pm","Judge":"MRS PAULA HARTINGER (44)","Number":2,"Count":7,"BreedName":"Rhodesian Ridgebacks ","DogCount":1,"BitchCount":2,"SpecialDogCount":2,"SpecialBitchCount":2,"CountAhead":18},{"BlockStart":"12:50 pm","Judge":"MRS PAULA HARTINGER (44)","Number":2,"Count":10,"BreedName":"Afghan Hounds ","DogCount":7,"BitchCount":1,"SpecialDogCount":1,"SpecialBitchCount":1,"CountAhead":25},{"BlockStart":"12:50 pm","Judge":"MRS PAULA HARTINGER (44)","Number":2,"Count":1,"BreedName":"Bluetick Coonhounds ","DogCount":0,"BitchCount":1,"SpecialDogCount":0,"SpecialBitchCount":0,"CountAhead":35},{"BlockStart":"12:50 pm","Judge":"MRS PAULA HARTINGER (44)","Number":2,"Count":1,"BreedName":"English Foxhounds ","DogCount":1,"BitchCount":0,"SpecialDogCount":0,"SpecialBitchCount":0,"CountAhead":36},{"BlockStart":"12:50 pm","Judge":"MRS PAULA HARTINGER (44)","Number":2,"Count":1,"BreedName":"Redbone Coonhounds ","DogCount":1,"BitchCount":0,"SpecialDogCount":0,"SpecialBitchCount":0,"CountAhead":37},{"BlockStart":"12:50 pm","Judge":"MRS PAULA HARTINGER (44)","Number":2,"Count":1,"BreedName":"Treeing Walker Coonhounds ","DogCount":0,"BitchCount":0,"SpecialDogCount":1,"SpecialBitchCount":0,"CountAhead":38},{"BlockStart":"12:50 pm","Judge":"MRS PAULA HARTINGER (44)","Number":2,"Count":1,"BreedName":"Greyhounds ","DogCount":0,"BitchCount":0,"SpecialDogCount":0,"SpecialBitchCount":1,"CountAhead":39},{"BlockStart":"12:50 pm","Judge":"MRS PAULA HARTINGER (44)","Number":2,"Count":1,"BreedName":"Bloodhounds ","DogCount":0,"BitchCount":0,"SpecialDogCount":0,"SpecialBitchCount":1,"CountAhead":40},{"BlockStart":"12:50 pm","Judge":"MRS PAULA HARTINGER (44)","Number":2,"Count":1,"BreedName":"Salukis ","DogCount":0,"BitchCount":0,"SpecialDogCount":1,"SpecialBitchCount":0,"CountAhead":41},{"BlockStart":"12:50 pm","Judge":"MRS PAULA HARTINGER (44)","Number":2,"Count":2,"BreedName":"Berger Picards (Misc. Dogs)","CountAhead":42},{"BlockStart":"8:30 am","Judge":"MR JASON HOKE (138)","Number":3,"Count":9,"BreedName":"Pugs ","DogCount":2,"BitchCount":6,"SpecialDogCount":1,"SpecialBitchCount":0,"CountAhead":0},{"BlockStart":"8:30 am","Judge":"MR JASON HOKE (138)","Number":3,"Count":2,"BreedName":"Beagles (13 Inch) ","DogCount":0,"BitchCount":1,"SpecialDogCount":0,"SpecialBitchCount":1,"CountAhead":9},{"BlockStart":"8:30 am","Judge":"MR JASON HOKE (138)","Number":3,"Count":5,"BreedName":"Beagles (15 Inch) ","DogCount":2,"BitchCount":0,"SpecialDogCount":3,"SpecialBitchCount":0,"CountAhead":11},{"BlockStart":"8:30 am","Judge":"MR JASON HOKE (138)","Number":3,"Count":6,"BreedName":"Chihuahuas (Smooth Coat) ","DogCount":2,"BitchCount":2,"SpecialDogCount":1,"SpecialBitchCount":1,"CountAhead":16},{"BlockStart":"8:30 am","Judge":"MR JASON HOKE (138)","Number":3,"Count":3,"BreedName":"Toy Fox Terriers ","DogCount":0,"BitchCount":0,"SpecialDogCount":1,"SpecialBitchCount":2,"CountAhead":22},{"BlockStart":"9:30 am","Judge":"MR JASON HOKE (138)","Number":3,"Count":3,"BreedName":"Boston Terriers ","DogCount":0,"BitchCount":0,"SpecialDogCount":2,"SpecialBitchCount":1,"CountAhead":0},{"BlockStart":"9:30 am","Judge":"MR JASON HOKE (138)","Number":3,"Count":9,"BreedName":"Chihuahuas (Long Coat) ","DogCount":4,"BitchCount":1,"SpecialDogCount":2,"SpecialBitchCount":2,"CountAhead":3},{"BlockStart":"9:30 am","Judge":"MR JASON HOKE (138)","Number":3,"Count":2,"BreedName":"Brussels Griffons ","DogCount":0,"BitchCount":0,"SpecialDogCount":1,"SpecialBitchCount":1,"CountAhead":12},{"BlockStart":"9:30 am","Judge":"MR JASON HOKE (138)","Number":3,"Count":17,"BreedName":"Cavalier King Charles Spaniels ","DogCount":3,"BitchCount":6,"SpecialDogCount":4,"SpecialBitchCount":4,"CountAhead":14},{"BlockStart":"10:45 am","Judge":"MR JASON HOKE (138)","Number":3,"Count":2,"BreedName":"Papillons ","DogCount":0,"BitchCount":0,"SpecialDogCount":2,"SpecialBitchCount":0,"CountAhead":0},{"BlockStart":"10:45 am","Judge":"MR JASON HOKE (138)","Number":3,"Count":5,"BreedName":"Poodles (Toy) ","DogCount":1,"BitchCount":3,"SpecialDogCount":0,"SpecialBitchCount":1,"CountAhead":2},{"BlockStart":"10:45 am","Judge":"MR JASON HOKE (138)","Number":3,"Count":18,"BreedName":"Chinese Cresteds ","DogCount":4,"BitchCount":9,"SpecialDogCount":2,"SpecialBitchCount":3,"CountAhead":7},{"BlockStart":"12:30 pm","Judge":"MR JASON HOKE (138)","Number":3,"Count":8,"BreedName":"Poodles (Standard) ","DogCount":1,"BitchCount":5,"SpecialDogCount":1,"SpecialBitchCount":1,"CountAhead":0},{"BlockStart":"12:30 pm","Judge":"MR JASON HOKE (138)","Number":3,"Count":3,"BreedName":"Shih Tzu ","DogCount":0,"BitchCount":2,"SpecialDogCount":0,"SpecialBitchCount":1,"CountAhead":8},{"BlockStart":"12:30 pm","Judge":"MR JASON HOKE (138)","Number":3,"Count":10,"BreedName":"Havanese ","DogCount":2,"BitchCount":6,"SpecialDogCount":1,"SpecialBitchCount":1,"CountAhead":11},{"BlockStart":"12:30 pm","Judge":"MR JASON HOKE (138)","Number":3,"Count":18,"BreedName":"Pomeranians ","DogCount":6,"BitchCount":8,"SpecialDogCount":3,"SpecialBitchCount":1,"CountAhead":21},{"BlockStart":"12:30 pm","Judge":"MR JASON HOKE (138)","Number":3,"Count":1,"BreedName":"Maltese ","DogCount":0,"BitchCount":0,"SpecialDogCount":1,"SpecialBitchCount":0,"CountAhead":39},{"BlockStart":"12:30 pm","Judge":"MR JASON HOKE (138)","Number":3,"Count":3,"BreedName":"Lhasa Apsos ","DogCount":2,"BitchCount":0,"SpecialDogCount":0,"SpecialBitchCount":1,"CountAhead":40},{"BlockStart":"12:30 pm","Judge":"MR JASON HOKE (138)","Number":3,"Count":14,"BreedName":"Poodles (Miniature) ","DogCount":4,"BitchCount":6,"SpecialDogCount":2,"SpecialBitchCount":2,"CountAhead":43},{"BlockStart":"8:30 am","Judge":"MR ROGER R HARTINGER (101)","Number":4,"Count":13,"BreedName":"French Bulldogs ","DogCount":3,"BitchCount":7,"SpecialDogCount":2,"SpecialBitchCount":0,"CountAhead":0},{"BlockStart":"8:30 am","Judge":"MR ROGER R HARTINGER (101)","Number":4,"Count":1,"IsVeteran":true,"BreedName":"French Bulldogs ","CountAhead":13},{"BlockStart":"8:30 am","Judge":"MR ROGER R HARTINGER (101)","Number":4,"Count":6,"BreedName":"Bulldogs ","DogCount":2,"BitchCount":3,"SpecialDogCount":0,"SpecialBitchCount":1,"CountAhead":14},{"BlockStart":"8:30 am","Judge":"MR ROGER R HARTINGER (101)","Number":4,"Count":4,"BreedName":"Chinese Shar-Pei ","DogCount":1,"BitchCount":1,"SpecialDogCount":0,"SpecialBitchCount":1,"CountAhead":20},{"BlockStart":"8:30 am","Judge":"MR ROGER R HARTINGER (101)","Number":4,"Count":1,"IsVeteran":true,"BreedName":"Chinese Shar-Pei ","CountAhead":24},{"BlockStart":"8:30 am","Judge":"MR ROGER R HARTINGER (101)","Number":4,"Count":8,"BreedName":"Vizslas ","DogCount":2,"BitchCount":3,"SpecialDogCount":0,"SpecialBitchCount":3,"CountAhead":25},{"BlockStart":"9:45 am","Judge":"MR ROGER R HARTINGER (101)","Number":4,"Count":2,"BreedName":"American Staffordshire Terriers ","DogCount":1,"BitchCount":0,"SpecialDogCount":1,"SpecialBitchCount":0,"CountAhead":0},{"BlockStart":"9:45 am","Judge":"MR ROGER R HARTINGER (101)","Number":4,"Count":6,"BreedName":"Australian Cattle Dogs ","DogCount":0,"BitchCount":4,"SpecialDogCount":1,"SpecialBitchCount":1,"CountAhead":2},{"BlockStart":"9:45 am","Judge":"MR ROGER R HARTINGER (101)","Number":4,"Count":14,"BreedName":"Pointers (German Shorthaired) ","DogCount":6,"BitchCount":3,"SpecialDogCount":3,"SpecialBitchCount":2,"CountAhead":8},{"BlockStart":"9:45 am","Judge":"MR ROGER R HARTINGER (101)","Number":4,"Count":3,"BreedName":"Setters (Gordon) ","DogCount":0,"BitchCount":2,"SpecialDogCount":1,"SpecialBitchCount":0,"CountAhead":22},{"BlockStart":"10:45 am","Judge":"MR ROGER R HARTINGER (101)","Number":4,"Count":3,"BreedName":"Retrievers (Chesapeake Bay) ","DogCount":2,"BitchCount":1,"SpecialDogCount":0,"SpecialBitchCount":0,"CountAhead":0},{"BlockStart":"10:45 am","Judge":"MR ROGER R HARTINGER (101)","Number":4,"Count":2,"BreedName":"Keeshonden ","DogCount":0,"BitchCount":0,"SpecialDogCount":2,"SpecialBitchCount":0,"CountAhead":3},{"BlockStart":"10:45 am","Judge":"MR ROGER R HARTINGER (101)","Number":4,"Count":7,"BreedName":"Airedale Terriers ","DogCount":2,"BitchCount":4,"SpecialDogCount":1,"SpecialBitchCount":0,"CountAhead":5},{"BlockStart":"10:45 am","Judge":"MR ROGER R HARTINGER (101)","Number":4,"Count":2,"BreedName":"Bouviers des Flandres ","DogCount":1,"BitchCount":0,"SpecialDogCount":1,"SpecialBitchCount":0,"CountAhead":12},{"BlockStart":"10:45 am","Judge":"MR ROGER R HARTINGER (101)","Number":4,"Count":4,"BreedName":"Setters (English) ","DogCount":2,"BitchCount":0,"SpecialDogCount":1,"SpecialBitchCount":1,"CountAhead":14},{"BlockStart":"10:45 am","Judge":"MR ROGER R HARTINGER (101)","Number":4,"Count":1,"BreedName":"Brittanys ","DogCount":0,"BitchCount":0,"SpecialDogCount":1,"SpecialBitchCount":0,"CountAhead":18},{"BlockStart":"10:45 am","Judge":"MR ROGER R HARTINGER (101)","Number":4,"Count":1,"BreedName":"Dalmatians ","DogCount":0,"BitchCount":0,"SpecialDogCount":1,"SpecialBitchCount":0,"CountAhead":19},{"BlockStart":"10:45 am","Judge":"MR ROGER R HARTINGER (101)","Number":4,"Count":1,"BreedName":"Setters (Irish Red And White) ","DogCount":0,"BitchCount":0,"SpecialDogCount":1,"SpecialBitchCount":0,"CountAhead":20},{"BlockStart":"10:45 am","Judge":"MR ROGER R HARTINGER (101)","Number":4,"Count":2,"BreedName":"Fox Terriers (Smooth) ","DogCount":0,"BitchCount":0,"SpecialDogCount":0,"SpecialBitchCount":2,"CountAhead":21},{"BlockStart":"10:45 am","Judge":"MR ROGER R HARTINGER (101)","Number":4,"Count":3,"BreedName":"Cairn Terriers ","DogCount":1,"BitchCount":1,"SpecialDogCount":0,"SpecialBitchCount":1,"CountAhead":23},{"BlockStart":"11:45 am","Judge":"MR ROGER R HARTINGER (101)","Number":4,"Count":2,"BreedName":"Fox Terriers (Wire) ","DogCount":0,"BitchCount":1,"SpecialDogCount":0,"SpecialBitchCount":1,"CountAhead":0},{"BlockStart":"11:45 am","Judge":"MR ROGER R HARTINGER (101)","Number":4,"Count":2,"BreedName":"Shiba Inu ","DogCount":0,"BitchCount":2,"SpecialDogCount":0,"SpecialBitchCount":0,"CountAhead":2},{"BlockStart":"11:45 am","Judge":"MR ROGER R HARTINGER (101)","Number":4,"Count":7,"BreedName":"Tibetan Terriers ","DogCount":2,"BitchCount":3,"SpecialDogCount":2,"SpecialBitchCount":0,"CountAhead":4},{"BlockStart":"11:45 am","Judge":"MR ROGER R HARTINGER (101)","Number":4,"Count":2,"BreedName":"Bichons Frises ","DogCount":0,"BitchCount":0,"SpecialDogCount":1,"SpecialBitchCount":1,"CountAhead":11},{"BlockStart":"11:45 am","Judge":"MR ROGER R HARTINGER (101)","Number":4,"Count":1,"BreedName":"Lowchen ","DogCount":0,"BitchCount":0,"SpecialDogCount":1,"SpecialBitchCount":0,"CountAhead":13},{"BlockStart":"11:45 am","Judge":"MR ROGER R HARTINGER (101)","Number":4,"Count":1,"BreedName":"Miniature Bull Terriers ","DogCount":0,"BitchCount":0,"SpecialDogCount":1,"SpecialBitchCount":0,"CountAhead":14},{"BlockStart":"11:45 am","Judge":"MR ROGER R HARTINGER (101)","Number":4,"Count":1,"BreedName":"Border Terriers ","DogCount":1,"BitchCount":0,"SpecialDogCount":0,"SpecialBitchCount":0,"CountAhead":15},{"BlockStart":"11:45 am","Judge":"MR ROGER R HARTINGER (101)","Number":4,"Count":1,"BreedName":"Lakeland Terriers ","DogCount":1,"BitchCount":0,"SpecialDogCount":0,"SpecialBitchCount":0,"CountAhead":16},{"BlockStart":"11:45 am","Judge":"MR ROGER R HARTINGER (101)","Number":4,"Count":1,"BreedName":"Miniature Schnauzers ","DogCount":0,"BitchCount":0,"SpecialDogCount":1,"SpecialBitchCount":0,"CountAhead":17},{"BlockStart":"11:45 am","Judge":"MR ROGER R HARTINGER (101)","Number":4,"Count":1,"BreedName":"Staffordshire Bull Terriers ","DogCount":0,"BitchCount":1,"SpecialDogCount":0,"SpecialBitchCount":0,"CountAhead":18},{"BlockStart":"12:30 pm","Judge":"MS LINN KLINGEL-BROWN (54)","Number":4,"Count":4,"BreedName":"Collies (Rough) ","DogCount":3,"BitchCount":1,"SpecialDogCount":0,"SpecialBitchCount":0,"CountAhead":0},{"BlockStart":"12:30 pm","Judge":"MS LINN KLINGEL-BROWN (54)","Number":4,"Count":11,"BreedName":"Australian Shepherds ","DogCount":4,"BitchCount":4,"SpecialDogCount":3,"SpecialBitchCount":0,"CountAhead":4},{"BlockStart":"12:30 pm","Judge":"MS LINN KLINGEL-BROWN (54)","Number":4,"Count":6,"BreedName":"German Shepherd Dogs ","DogCount":2,"BitchCount":2,"SpecialDogCount":2,"SpecialBitchCount":0,"CountAhead":15},{"BlockStart":"12:30 pm","Judge":"MS LINN KLINGEL-BROWN (54)","Number":4,"Count":2,"BreedName":"Old English Sheepdogs ","DogCount":0,"BitchCount":1,"SpecialDogCount":0,"SpecialBitchCount":1,"CountAhead":21},{"BlockStart":"12:30 pm","Judge":"MS LINN KLINGEL-BROWN (54)","Number":4,"Count":10,"BreedName":"Border Collies ","DogCount":3,"BitchCount":6,"SpecialDogCount":0,"SpecialBitchCount":1,"CountAhead":23},{"BlockStart":"12:30 pm","Judge":"MS LINN KLINGEL-BROWN (54)","Number":4,"Count":1,"BreedName":"Collies (Smooth) ","DogCount":0,"BitchCount":1,"SpecialDogCount":0,"SpecialBitchCount":0,"CountAhead":33},{"BlockStart":"12:30 pm","Judge":"MS LINN KLINGEL-BROWN (54)","Number":4,"Count":6,"BreedName":"Pembroke Welsh Corgis ","DogCount":2,"BitchCount":3,"SpecialDogCount":1,"SpecialBitchCount":0,"CountAhead":34},{"BlockStart":"12:30 pm","Judge":"MS LINN KLINGEL-BROWN (54)","Number":4,"Count":7,"BreedName":"Shetland Sheepdogs ","DogCount":2,"BitchCount":4,"SpecialDogCount":1,"SpecialBitchCount":0,"CountAhead":40},{"BlockStart":"12:30 pm","Judge":"MS LINN KLINGEL-BROWN (54)","Number":4,"Count":7,"BreedName":"Cardigan Welsh Corgis ","DogCount":0,"BitchCount":3,"SpecialDogCount":2,"SpecialBitchCount":2,"CountAhead":47},{"Empty":"obedience: not captured","BlockStart":"8:30 am","Judge":"MR CHARLES W KLINE (18)","Number":5},{"Empty":"obedience: not captured","BlockStart":"8:50 am","Judge":"MR CHARLES W KLINE (18)","Number":5},{"Empty":"obedience: not captured","BlockStart":"9:20 am","Judge":"MR CHARLES W KLINE (18)","Number":5},{"Empty":"obedience: not captured","BlockStart":"9:35 am","Judge":"MR CHARLES W KLINE (18)","Number":5},{"Empty":"obedience: not captured","BlockStart":"10:10 am","Judge":"MR CHARLES W KLINE (18)","Number":5},{"Empty":"obedience: not captured","BlockStart":"10:55 am","Judge":"MRS ANNA LORENZ (9)","Number":5},{"Empty":"obedience: not captured","BlockStart":"11:35 am","Judge":"MRS ANNA LORENZ (9)","Number":5},{"Empty":"rally: not captured","BlockStart":"11:55 am","Judge":"MRS ANNA LORENZ (9)","Number":5},{"Empty":"rally: not captured","BlockStart":"12:40 pm","Judge":"MRS ANNA LORENZ (25)","Number":5},{"Empty":"rally: not captured","BlockStart":"12:50 pm","Judge":"MRS ANNA LORENZ (25)","Number":5},{"Empty":"rally: not captured","BlockStart":"12:50 pm","Judge":"MRS ANNA LORENZ (25)","Number":5},{"Empty":"rally: not captured","BlockStart":"12:50 pm","Judge":"MRS ANNA LORENZ (25)","Number":5},{"Empty":"rally: not captured","BlockStart":"12:50 pm","Judge":"MRS ANNA LORENZ (25)","Number":5},{"Empty":"rally: not captured","BlockStart":"12:50 pm","Judge":"MRS ANNA LORENZ (25)","Number":5},{"Empty":"rally: not captured","BlockStart":"12:50 pm","Judge":"MRS ANNA LORENZ (25)","Number":5},{"Empty":"rally: not captured","BlockStart":"12:50 pm","Judge":"MRS ANNA LORENZ (25)","Number":5},{"Group":"SPORTING GROUP","Judge":"MRS PAULA HARTINGER","Time":"2:15 pm"},{"Group":"HOUND GROUP","Judge":"MR ROGER R HARTINGER","Time":"2:15 pm"},{"Group":"TERRIER GROUP","Judge":"MRS PAULA HARTINGER","Time":"2:15 pm"},{"Group":"WORKING GROUP","Judge":"MR ROGER R HARTINGER","Time":"2:15 pm"},{"Group":"HERDING GROUP","Judge":"MRS PAULA HARTINGER","Time":"2:15 pm"},{"Group":"TOY GROUP","Judge":"MR ROGER R HARTINGER","Time":"2:15 pm"},{"Group":"NON-SPORTING GROUP","Judge":"MRS PAULA HARTINGER","Time":"2:15 pm"},{"Group":"BEST IN SHOW","Judge":"MRS PAULA HARTINGER","Time":"2:15 pm"},{"BlockStart":"8:00 am","Judge":"MS GRACE M FRITZ (74)","Number":1,"Count":3,"BreedName":"Boston Terriers ","DogCount":0,"BitchCount":0,"SpecialDogCount":2,"SpecialBitchCount":1,"CountAhead":0},{"BlockStart":"8:00 am","Judge":"MS GRACE M FRITZ (74)","Number":1,"Count":13,"BreedName":"French Bulldogs ","DogCount":3,"BitchCount":7,"SpecialDogCount":2,"SpecialBitchCount":0,"CountAhead":3},{"BlockStart":"8:00 am","Judge":"MS GRACE M FRITZ (74)","Number":1,"Count":1,"IsVeteran":true,"BreedName":"French Bulldogs ","CountAhead":16},{"BlockStart":"8:00 am","Judge":"MS GRACE M FRITZ (74)","Number":1,"Count":3,"BreedName":"Shiba Inu ","DogCount":0,"BitchCount":3,"SpecialDogCount":0,"SpecialBitchCount":0,"CountAhead":17},{"BlockStart":"8:00 am","Judge":"MS GRACE M FRITZ (74)","Number":1,"Count":7,"BreedName":"Bulldogs ","DogCount":3,"BitchCount":3,"SpecialDogCount":0,"SpecialBitchCount":1,"CountAhead":20},{"BlockStart":"9:00 am","Judge":"MS GRACE M FRITZ (74)","Number":1,"Count":4,"BreedName":"Chinese Shar-Pei ","DogCount":1,"BitchCount":1,"SpecialDogCount":0,"SpecialBitchCount":1,"CountAhead":0},{"BlockStart":"9:00 am","Judge":"MS GRACE M FRITZ (74)","Number":1,"Count":1,"IsVeteran":true,"BreedName":"Chinese Shar-Pei ","CountAhead":4},{"BlockStart":"9:00 am","Judge":"MS GRACE M FRITZ (74)","Number":1,"Count":2,"BreedName":"Keeshonden ","DogCount":0,"BitchCount":0,"SpecialDogCount":2,"SpecialBitchCount":0,"CountAhead":5},{"BlockStart":"9:00 am","Judge":"MS GRACE M FRITZ (74)","Number":1,"Count":3,"BreedName":"Poodles (Toy) ","DogCount":1,"BitchCount":1,"SpecialDogCount":0,"SpecialBitchCount":1,"CountAhead":7},{"BlockStart":"9:00 am","Judge":"MS GRACE M FRITZ (74)","Number":1,"Count":7,"BreedName":"Tibetan Terriers ","DogCount":2,"BitchCount":3,"SpecialDogCount":2,"SpecialBitchCount":0,"CountAhead":10},{"BlockStart":"9:00 am","Judge":"MS GRACE M FRITZ (74)","Number":1,"Count":3,"BreedName":"Lhasa Apsos ","DogCount":2,"BitchCount":0,"SpecialDogCount":0,"SpecialBitchCount":1,"CountAhead":17},{"BlockStart":"9:50 am","Judge":"DR EDNA K MARTIN (49)","Number":1,"Count":7,"BreedName":"Rhodesian Ridgebacks ","DogCount":1,"BitchCount":2,"SpecialDogCount":2,"SpecialBitchCount":2,"CountAhead":0},{"BlockStart":"9:50 am","Judge":"DR EDNA K MARTIN (49)","Number":1,"Count":2,"BreedName":"American Staffordshire Terriers ","DogCount":1,"BitchCount":0,"SpecialDogCount":1,"SpecialBitchCount":0,"CountAhead":7},{"BlockStart":"9:50 am","Judge":"DR EDNA K MARTIN (49)","Number":1,"Count":7,"BreedName":"Airedale Terriers ","DogCount":1,"BitchCount":5,"SpecialDogCount":1,"SpecialBitchCount":0,"CountAhead":9},{"BlockStart":"9:50 am","Judge":"DR EDNA K MARTIN (49)","Number":1,"Count":2,"BreedName":"Fox Terriers (Smooth) ","DogCount":0,"BitchCount":0,"SpecialDogCount":0,"SpecialBitchCount":2,"CountAhead":16},{"BlockStart":"9:50 am","Judge":"DR EDNA K MARTIN (49)","Number":1,"Count":3,"BreedName":"Cairn Terriers ","DogCount":1,"BitchCount":1,"SpecialDogCount":0,"SpecialBitchCount":1,"CountAhead":18},{"BlockStart":"9:50 am","Judge":"DR EDNA K MARTIN (49)","Number":1,"Count":2,"BreedName":"Scottish Terriers ","DogCount":1,"BitchCount":0,"SpecialDogCount":1,"SpecialBitchCount":0,"CountAhead":21},{"BlockStart":"9:50 am","Judge":"DR EDNA K MARTIN (49)","Number":1,"Count":2,"BreedName":"Fox Terriers (Wire) ","DogCount":0,"BitchCount":1,"SpecialDogCount":0,"SpecialBitchCount":1,"CountAhead":23},{"BlockStart":"10:50 am","Judge":"DR EDNA K MARTIN (49)","Number":1,"Count":3,"BreedName":"Miniature Schnauzers ","DogCount":0,"BitchCount":2,"SpecialDogCount":1,"SpecialBitchCount":0,"CountAhead":0},{"BlockStart":"10:50 am","Judge":"DR EDNA K MARTIN (49)","Number":1,"Count":11,"BreedName":"Whippets ","DogCount":3,"BitchCount":3,"SpecialDogCount":2,"SpecialBitchCount":3,"CountAhead":3},{"BlockStart":"10:50 am","Judge":"DR EDNA K MARTIN (49)","Number":1,"Count":1,"BreedName":"Miniature Bull Terriers ","DogCount":0,"BitchCount":0,"SpecialDogCount":1,"SpecialBitchCount":0,"CountAhead":14},{"BlockStart":"10:50 am","Judge":"DR EDNA K MARTIN (49)","Number":1,"Count":1,"BreedName":"Border Terriers ","DogCount":1,"BitchCount":0,"SpecialDogCount":0,"SpecialBitchCount":0,"CountAhead":15},{"BlockStart":"10:50 am","Judge":"DR EDNA K MARTIN (49)","Number":1,"Count":1,"BreedName":"Norwich Terriers ","DogCount":0,"BitchCount":0,"SpecialDogCount":1,"SpecialBitchCount":0,"CountAhead":16},{"BlockStart":"10:50 am","Judge":"DR EDNA K MARTIN (49)","Number":1,"Count":1,"BreedName":"Lakeland Terriers ","DogCount":1,"BitchCount":0,"SpecialDogCount":0,"SpecialBitchCount":0,"CountAhead":17},{"BlockStart":"10:50 am","Judge":"DR EDNA K MARTIN (49)","Number":1,"Count":1,"BreedName":"Staffordshire Bull Terriers ","DogCount":0,"BitchCount":1,"SpecialDogCount":0,"SpecialBitchCount":0,"CountAhead":18},{"BlockStart":"10:50 am","Judge":"DR EDNA K MARTIN (49)","Number":1,"Count":1,"BreedName":"Kerry Blue Terriers ","DogCount":0,"BitchCount":0,"SpecialDogCount":0,"SpecialBitchCount":1,"CountAhead":19},{"BlockStart":"10:50 am","Judge":"DR EDNA K MARTIN (49)","Number":1,"Count":1,"BreedName":"Redbone Coonhounds ","DogCount":1,"BitchCount":0,"SpecialDogCount":0,"SpecialBitchCount":0,"CountAhead":20},{"BlockStart":"10:50 am","Judge":"DR EDNA K MARTIN (49)","Number":1,"Count":1,"BreedName":"Treeing Walker Coonhounds ","DogCount":0,"BitchCount":0,"SpecialDogCount":1,"SpecialBitchCount":0,"CountAhead":21},{"BlockStart":"10:50 am","Judge":"DR EDNA K MARTIN (49)","Number":1,"Count":1,"BreedName":"Salukis ","DogCount":0,"BitchCount":0,"SpecialDogCount":1,"SpecialBitchCount":0,"CountAhead":22},{"BlockStart":"10:50 am","Judge":"DR EDNA K MARTIN (49)","Number":1,"Count":1,"BreedName":"Scottish Deerhounds ","DogCount":1,"BitchCount":0,"SpecialDogCount":0,"SpecialBitchCount":0,"CountAhead":23},{"BlockStart":"11:50 am","Judge":"MS GRACE M FRITZ\n","Number":1,"Count":13,"BreedName":"Poodles (Miniature) ","DogCount":4,"BitchCount":5,"SpecialDogCount":2,"SpecialBitchCount":2,"CountAhead":0},{"BlockStart":"11:50 am","Judge":"MS GRACE M FRITZ\n","Number":1,"Count":2,"BreedName":"Bichons Frises ","DogCount":0,"BitchCount":0,"SpecialDogCount":1,"SpecialBitchCount":1,"CountAhead":13},{"BlockStart":"11:50 am","Judge":"MS GRACE M FRITZ\n","Number":1,"Count":1,"BreedName":"Lowchen ","DogCount":0,"BitchCount":0,"SpecialDogCount":1,"SpecialBitchCount":0,"CountAhead":15},{"BlockStart":"11:50 am","Judge":"MS GRACE M FRITZ\n","Number":1,"Count":2,"BreedName":"Berger Picards (Misc. Dogs)","CountAhead":16},{"BlockStart":"11:50 am","Judge":"MS GRACE M FRITZ\n","Number":1,"Count":1,"BreedName":"Dalmatians ","DogCount":0,"BitchCount":0,"SpecialDogCount":1,"SpecialBitchCount":0,"CountAhead":18},{"BlockStart":"11:50 am","Judge":"MS GRACE M FRITZ\n","Number":1,"Count":10,"BreedName":"Poodles (Standard) ","DogCount":3,"BitchCount":5,"SpecialDogCount":1,"SpecialBitchCount":1,"CountAhead":19},{"BlockStart":"8:00 am","Judge":"MRS MEGHEN RIESE BASSEL (91)","Number":2,"Count":9,"BreedName":"Weimaraners ","DogCount":3,"BitchCount":4,"SpecialDogCount":0,"SpecialBitchCount":2,"CountAhead":0},{"BlockStart":"8:00 am","Judge":"MRS MEGHEN RIESE BASSEL (91)","Number":2,"Count":6,"BreedName":"Retrievers (Labrador) ","DogCount":2,"BitchCount":1,"SpecialDogCount":2,"SpecialBitchCount":0,"CountAhead":9},{"BlockStart":"8:00 am","Judge":"MRS MEGHEN RIESE BASSEL (91)","Number":2,"Count":1,"IsVeteran":true,"BreedName":"Retrievers (Labrador) ","CountAhead":15},{"BlockStart":"8:00 am","Judge":"MRS MEGHEN RIESE BASSEL (91)","Number":2,"Count":12,"BreedName":"Retrievers (Nova Scotia Duck Tolling) ","DogCount":3,"BitchCount":6,"SpecialDogCount":1,"SpecialBitchCount":2,"CountAhead":16},{"BlockStart":"9:05 am","Judge":"MRS MEGHEN RIESE BASSEL (91)","Number":2,"Count":8,"BreedName":"Spaniels (Welsh Springer) ","DogCount":1,"BitchCount":2,"SpecialDogCount":2,"SpecialBitchCount":2,"CountAhead":0},{"BlockStart":"9:05 am","Judge":"MRS MEGHEN RIESE BASSEL (91)","Number":2,"Count":1,"IsVeteran":true,"BreedName":"Spaniels (Welsh Springer) ","CountAhead":8},{"BlockStart":"9:05 am","Judge":"MRS MEGHEN RIESE BASSEL (91)","Number":2,"Count":2,"BreedName":"Retrievers (Curly-Coated) ","DogCount":0,"BitchCount":1,"SpecialDogCount":0,"SpecialBitchCount":0,"CountAhead":9},{"BlockStart":"9:05 am","Judge":"MRS MEGHEN RIESE BASSEL (91)","Number":2,"Count":1,"IsVeteran":true,"BreedName":"Retrievers (Curly-Coated) ","CountAhead":11},{"BlockStart":"9:05 am","Judge":"MRS MEGHEN RIESE BASSEL (91)","Number":2,"Count":3,"BreedName":"Spaniels (English Springer) ","DogCount":1,"BitchCount":0,"SpecialDogCount":1,"SpecialBitchCount":1,"CountAhead":12},{"BlockStart":"9:05 am","Judge":"MRS MEGHEN RIESE BASSEL (91)","Number":2,"Count":11,"BreedName":"Retrievers (Golden) ","DogCount":6,"BitchCount":4,"SpecialDogCount":1,"SpecialBitchCount":0,"CountAhead":15},{"BlockStart":"9:05 am","Judge":"MRS MEGHEN RIESE BASSEL (91)","Number":2,"Count":8,"BreedName":"Spaniels (Irish Water) ","DogCount":2,"BitchCount":5,"SpecialDogCount":1,"SpecialBitchCount":0,"CountAhead":26},{"BlockStart":"10:20 am","Judge":"MRS MEGHEN RIESE BASSEL (91)","Number":2,"Count":2,"BreedName":"Spaniels (American Water) ","DogCount":2,"BitchCount":0,"SpecialDogCount":0,"SpecialBitchCount":0,"CountAhead":0},{"BlockStart":"10:20 am","Judge":"MRS MEGHEN RIESE BASSEL (91)","Number":2,"Count":10,"BreedName":"Spaniels (English Cocker) ","DogCount":4,"BitchCount":5,"SpecialDogCount":0,"SpecialBitchCount":1,"CountAhead":2},{"BlockStart":"10:20 am","Judge":"MRS MEGHEN RIESE BASSEL (91)","Number":2,"Count":5,"BreedName":"Dachshunds (Smooth) ","DogCount":2,"BitchCount":2,"SpecialDogCount":0,"SpecialBitchCount":1,"CountAhead":12},{"BlockStart":"10:20 am","Judge":"MRS MEGHEN RIESE BASSEL (91)","Number":2,"Count":1,"BreedName":"Dachshunds (Wirehaired) ","DogCount":1,"BitchCount":0,"SpecialDogCount":0,"SpecialBitchCount":0,"CountAhead":17},{"BlockStart":"11:05 am","Judge":"MR JASON HOKE (38)","Number":2,"Count":15,"BreedName":"Pointers (German Shorthaired) ","DogCount":6,"BitchCount":4,"SpecialDogCount":3,"SpecialBitchCount":2,"CountAhead":0},{"BlockStart":"11:05 am","Judge":"MR JASON HOKE (38)","Number":2,"Count":4,"ClassName":"Open Senior","CountAhead":15},{"BlockStart":"11:05 am","Judge":"MR JASON HOKE (38)","Number":2,"Count":10,"ClassName":"Open Intermediate","CountAhead":19},{"BlockStart":"11:05 am","Judge":"MR JASON HOKE (38)","Number":2,"Count":5,"ClassName":"Open Junior","CountAhead":29},{"BlockStart":"11:05 am","Judge":"MR JASON HOKE (38)","Number":2,"Count":2,"ClassName":"Novice Intermediate","CountAhead":34},{"BlockStart":"11:05 am","Judge":"MR JASON HOKE (38)","Number":2,"Count":2,"ClassName":"Novice Junior","CountAhead":36},{"BlockStart":"12:50 pm","Judge":"MRS MEGHEN RIESE BASSEL\n","Number":2,"Count":4,"BreedName":"Spaniels (Cocker) Parti-Color","DogCount":0,"BitchCount":2,"SpecialDogCount":1,"SpecialBitchCount":1,"CountAhead":0},{"BlockStart":"12:50 pm","Judge":"MRS MEGHEN RIESE BASSEL\n","Number":2,"Count":4,"BreedName":"Spaniels (Cocker) Ascob","DogCount":0,"BitchCount":3,"SpecialDogCount":1,"SpecialBitchCount":0,"CountAhead":4},{"BlockStart":"12:50 pm","Judge":"MRS MEGHEN RIESE BASSEL\n","Number":2,"Count":1,"BreedName":"Retrievers (Flat-Coated) ","DogCount":0,"BitchCount":0,"SpecialDogCount":1,"SpecialBitchCount":0,"CountAhead":8},{"BlockStart":"12:50 pm","Judge":"MRS MEGHEN RIESE BASSEL\n","Number":2,"Count":1,"BreedName":"Spaniels (Clumber) ","DogCount":0,"BitchCount":0,"SpecialDogCount":1,"SpecialBitchCount":0,"CountAhead":9},{"BlockStart":"12:50 pm","Judge":"MRS MEGHEN RIESE BASSEL\n","Number":2,"Count":4,"BreedName":"Spaniels (Cocker) Black","DogCount":0,"BitchCount":1,"SpecialDogCount":2,"SpecialBitchCount":1,"CountAhead":10},{"BlockStart":"8:00 am","Judge":"MR ROGER R HARTINGER (132)","Number":3,"Count":9,"BreedName":"Pugs ","DogCount":2,"BitchCount":6,"SpecialDogCount":1,"SpecialBitchCount":0,"CountAhead":0},{"BlockStart":"8:00 am","Judge":"MR ROGER R HARTINGER (132)","Number":3,"Count":18,"BreedName":"Great Danes ","DogCount":5,"BitchCount":8,"SpecialDogCount":4,"SpecialBitchCount":1,"CountAhead":9},{"BlockStart":"9:05 am","Judge":"MR ROGER R HARTINGER (132)","Number":3,"Count":2,"BreedName":"Bullmastiffs ","DogCount":0,"BitchCount":1,"SpecialDogCount":0,"SpecialBitchCount":1,"CountAhead":0},{"BlockStart":"9:05 am","Judge":"MR ROGER R HARTINGER (132)","Number":3,"Count":5,"BreedName":"Rottweilers ","DogCount":1,"BitchCount":2,"SpecialDogCount":2,"SpecialBitchCount":0,"CountAhead":2},{"BlockStart":"9:05 am","Judge":"MR ROGER R HARTINGER (132)","Number":3,"Count":16,"BreedName":"Boxers ","DogCount":8,"BitchCount":6,"SpecialDogCount":0,"SpecialBitchCount":2,"CountAhead":7},{"BlockStart":"9:05 am","Judge":"MR ROGER R HARTINGER (132)","Number":3,"Count":11,"BreedName":"Doberman Pinschers ","DogCount":4,"BitchCount":3,"SpecialDogCount":3,"SpecialBitchCount":1,"CountAhead":23},{"BlockStart":"10:25 am","Judge":"MR ROGER R HARTINGER (132)","Number":3,"Count":3,"BreedName":"Siberian Huskies ","DogCount":1,"BitchCount":1,"SpecialDogCount":1,"SpecialBitchCount":0,"CountAhead":0},{"BlockStart":"10:25 am","Judge":"MR ROGER R HARTINGER (132)","Number":3,"Count":2,"BreedName":"Akitas ","DogCount":0,"BitchCount":1,"SpecialDogCount":0,"SpecialBitchCount":0,"CountAhead":3},{"BlockStart":"10:25 am","Judge":"MR ROGER R HARTINGER (132)","Number":3,"Count":1,"IsVeteran":true,"BreedName":"Akitas ","CountAhead":5},{"BlockStart":"10:25 am","Judge":"MR ROGER R HARTINGER (132)","Number":3,"Count":4,"BreedName":"Bernese Mountain Dogs ","DogCount":1,"BitchCount":0,"SpecialDogCount":2,"SpecialBitchCount":0,"CountAhead":6},{"BlockStart":"10:25 am","Judge":"MR ROGER R HARTINGER (132)","Number":3,"Count":1,"IsVeteran":true,"BreedName":"Bernese Mountain Dogs ","CountAhead":10},{"BlockStart":"10:25 am","Judge":"MR ROGER R HARTINGER (132)","Number":3,"Count":15,"BreedName":"Newfoundlands ","DogCount":8,"BitchCount":3,"SpecialDogCount":1,"SpecialBitchCount":3,"CountAhead":11},{"BlockStart":"10:25 am","Judge":"MR ROGER R HARTINGER (132)","Number":3,"Count":13,"BreedName":"Samoyeds ","DogCount":3,"BitchCount":8,"SpecialDogCount":0,"SpecialBitchCount":2,"CountAhead":26},{"BlockStart":"11:55 am","Judge":"MS JOANNE M BUEHLER (17)","Number":3,"Count":6,"BreedName":"Basset Hounds ","DogCount":1,"BitchCount":3,"SpecialDogCount":1,"SpecialBitchCount":1,"CountAhead":0},{"BlockStart":"11:55 am","Judge":"MS JOANNE M BUEHLER (17)","Number":3,"Count":2,"BreedName":"Beagles (13 Inch) ","DogCount":0,"BitchCount":1,"SpecialDogCount":0,"SpecialBitchCount":1,"CountAhead":6},{"BlockStart":"11:55 am","Judge":"MS JOANNE M BUEHLER (17)","Number":3,"Count":3,"BreedName":"Irish Wolfhounds ","DogCount":1,"BitchCount":2,"SpecialDogCount":0,"SpecialBitchCount":0,"CountAhead":8},{"BlockStart":"11:55 am","Judge":"MS JOANNE M BUEHLER (17)","Number":3,"Count":1,"BreedName":"Greyhounds ","DogCount":0,"BitchCount":0,"SpecialDogCount":0,"SpecialBitchCount":1,"CountAhead":11},{"BlockStart":"11:55 am","Judge":"MS JOANNE M BUEHLER (17)","Number":3,"Count":5,"BreedName":"Beagles (15 Inch) ","DogCount":2,"BitchCount":0,"SpecialDogCount":3,"SpecialBitchCount":0,"CountAhead":12},{"BlockStart":"12:40 pm","Judge":"MR ROGER R HARTINGER\n","Number":3,"Count":6,"BreedName":"Giant Schnauzers ","DogCount":0,"BitchCount":5,"SpecialDogCount":1,"SpecialBitchCount":0,"CountAhead":0},{"BlockStart":"12:40 pm","Judge":"MR ROGER R HARTINGER\n","Number":3,"Count":9,"BreedName":"Afghan Hounds ","DogCount":6,"BitchCount":1,"SpecialDogCount":1,"SpecialBitchCount":1,"CountAhead":6},{"BlockStart":"12:40 pm","Judge":"MR ROGER R HARTINGER\n","Number":3,"Count":12,"BreedName":"Standard Schnauzers ","DogCount":5,"BitchCount":2,"SpecialDogCount":3,"SpecialBitchCount":2,"CountAhead":15},{"BlockStart":"12:40 pm","Judge":"MR ROGER R HARTINGER\n","Number":3,"Count":1,"BreedName":"German Pinschers ","DogCount":0,"BitchCount":0,"SpecialDogCount":1,"SpecialBitchCount":0,"CountAhead":27},{"BlockStart":"12:40 pm","Judge":"MR ROGER R HARTINGER\n","Number":3,"Count":1,"BreedName":"Bloodhounds ","DogCount":0,"BitchCount":0,"SpecialDogCount":0,"SpecialBitchCount":1,"CountAhead":28},{"BlockStart":"12:40 pm","Judge":"MR ROGER R HARTINGER\n","Number":3,"Count":1,"BreedName":"Bluetick Coonhounds ","DogCount":0,"BitchCount":1,"SpecialDogCount":0,"SpecialBitchCount":0,"CountAhead":29},{"BlockStart":"12:40 pm","Judge":"MR ROGER R HARTINGER\n","Number":3,"Count":1,"BreedName":"Alaskan Malamutes ","DogCount":0,"BitchCount":0,"SpecialDogCount":0,"SpecialBitchCount":1,"CountAhead":30},{"BlockStart":"12:40 pm","Judge":"MR ROGER R HARTINGER\n","Number":3,"Count":1,"BreedName":"Great Pyrenees ","DogCount":0,"BitchCount":0,"SpecialDogCount":1,"SpecialBitchCount":0,"CountAhead":31},{"BlockStart":"12:40 pm","Judge":"MR ROGER R HARTINGER\n","Number":3,"Count":1,"BreedName":"Portuguese Water Dogs ","DogCount":0,"BitchCount":1,"SpecialDogCount":0,"SpecialBitchCount":0,"CountAhead":32},{"BlockStart":"12:40 pm","Judge":"MR ROGER R HARTINGER\n","Number":3,"Count":1,"BreedName":"Tibetan Mastiffs ","DogCount":0,"BitchCount":1,"SpecialDogCount":0,"SpecialBitchCount":0,"CountAhead":33},{"BlockStart":"8:00 am","Judge":"MRS PAULA HARTINGER (175)","Number":4,"Count":6,"BreedName":"Australian Cattle Dogs ","DogCount":0,"BitchCount":4,"SpecialDogCount":1,"SpecialBitchCount":1,"CountAhead":0},{"BlockStart":"8:00 am","Judge":"MRS PAULA HARTINGER (175)","Number":4,"Count":11,"BreedName":"German Shepherd Dogs ","DogCount":4,"BitchCount":5,"SpecialDogCount":2,"SpecialBitchCount":0,"CountAhead":6},{"BlockStart":"8:00 am","Judge":"MRS PAULA HARTINGER (175)","Number":4,"Count":7,"BreedName":"Vizslas ","DogCount":2,"BitchCount":3,"SpecialDogCount":0,"SpecialBitchCount":2,"CountAhead":17},{"BlockStart":"8:00 am","Judge":"MRS PAULA HARTINGER (175)","Number":4,"Count":4,"BreedName":"Spinoni Italiani ","DogCount":1,"BitchCount":0,"SpecialDogCount":1,"SpecialBitchCount":2,"CountAhead":24},{"BlockStart":"8:00 am","Judge":"MRS PAULA HARTINGER (175)","Number":4,"Count":10,"BreedName":"Australian Shepherds ","DogCount":3,"BitchCount":4,"SpecialDogCount":3,"SpecialBitchCount":0,"CountAhead":28},{"BlockStart":"9:20 am","Judge":"MRS PAULA HARTINGER (175)","Number":4,"Count":10,"BreedName":"Border Collies ","DogCount":3,"BitchCount":6,"SpecialDogCount":0,"SpecialBitchCount":1,"CountAhead":0},{"BlockStart":"9:20 am","Judge":"MRS PAULA HARTINGER (175)","Number":4,"Count":5,"BreedName":"Collies (Rough) ","DogCount":4,"BitchCount":1,"SpecialDogCount":0,"SpecialBitchCount":0,"CountAhead":10},{"BlockStart":"9:20 am","Judge":"MRS PAULA HARTINGER (175)","Number":4,"Count":3,"BreedName":"Retrievers (Chesapeake Bay) ","DogCount":2,"BitchCount":1,"SpecialDogCount":0,"SpecialBitchCount":0,"CountAhead":15},{"BlockStart":"9:20 am","Judge":"MRS PAULA HARTINGER (175)","Number":4,"Count":3,"BreedName":"Setters (Gordon) ","DogCount":0,"BitchCount":2,"SpecialDogCount":1,"SpecialBitchCount":0,"CountAhead":18},{"BlockStart":"9:20 am","Judge":"MRS PAULA HARTINGER (175)","Number":4,"Count":7,"BreedName":"Cardigan Welsh Corgis ","DogCount":0,"BitchCount":3,"SpecialDogCount":2,"SpecialBitchCount":2,"CountAhead":21},{"BlockStart":"9:20 am","Judge":"MRS PAULA HARTINGER (175)","Number":4,"Count":6,"BreedName":"Chihuahuas (Smooth Coat) ","DogCount":2,"BitchCount":2,"SpecialDogCount":1,"SpecialBitchCount":1,"CountAhead":28},{"BlockStart":"10:30 am","Judge":"MRS PAULA HARTINGER (175)","Number":4,"Count":3,"BreedName":"Toy Fox Terriers ","DogCount":0,"BitchCount":0,"SpecialDogCount":1,"SpecialBitchCount":2,"CountAhead":0},{"BlockStart":"10:30 am","Judge":"MRS PAULA HARTINGER (175)","Number":4,"Count":6,"BreedName":"Pembroke Welsh Corgis ","DogCount":2,"BitchCount":3,"SpecialDogCount":1,"SpecialBitchCount":0,"CountAhead":3},{"BlockStart":"10:30 am","Judge":"MRS PAULA HARTINGER (175)","Number":4,"Count":8,"BreedName":"Chihuahuas (Long Coat) ","DogCount":4,"BitchCount":1,"SpecialDogCount":2,"SpecialBitchCount":1,"CountAhead":9},{"BlockStart":"10:30 am","Judge":"MRS PAULA HARTINGER (175)","Number":4,"Count":7,"BreedName":"Shetland Sheepdogs ","DogCount":2,"BitchCount":4,"SpecialDogCount":1,"SpecialBitchCount":0,"CountAhead":17},{"BlockStart":"10:30 am","Judge":"MRS PAULA HARTINGER (175)","Number":4,"Count":17,"BreedName":"Cavalier King Charles Spaniels ","DogCount":3,"BitchCount":6,"SpecialDogCount":4,"SpecialBitchCount":4,"CountAhead":24},{"BlockStart":"12:40 pm","Judge":"MRS PAULA HARTINGER (175)","Number":4,"Count":2,"BreedName":"Old English Sheepdogs ","DogCount":0,"BitchCount":1,"SpecialDogCount":0,"SpecialBitchCount":1,"CountAhead":0},{"BlockStart":"12:40 pm","Judge":"MRS PAULA HARTINGER (175)","Number":4,"Count":2,"BreedName":"Bouviers des Flandres ","DogCount":1,"BitchCount":0,"SpecialDogCount":1,"SpecialBitchCount":0,"CountAhead":2},{"BlockStart":"12:40 pm","Judge":"MRS PAULA HARTINGER (175)","Number":4,"Count":3,"BreedName":"Setters (English) ","DogCount":1,"BitchCount":0,"SpecialDogCount":1,"SpecialBitchCount":1,"CountAhead":4},{"BlockStart":"12:40 pm","Judge":"MRS PAULA HARTINGER (175)","Number":4,"Count":1,"BreedName":"Brittanys ","DogCount":0,"BitchCount":0,"SpecialDogCount":1,"SpecialBitchCount":0,"CountAhead":7},{"BlockStart":"12:40 pm","Judge":"MRS PAULA HARTINGER (175)","Number":4,"Count":1,"BreedName":"Setters (Irish Red And White) ","DogCount":0,"BitchCount":0,"SpecialDogCount":1,"SpecialBitchCount":0,"CountAhead":8},{"BlockStart":"12:40 pm","Judge":"MRS PAULA HARTINGER (175)","Number":4,"Count":2,"BreedName":"Papillons ","DogCount":0,"BitchCount":0,"SpecialDogCount":2,"SpecialBitchCount":0,"CountAhead":9},{"BlockStart":"12:40 pm","Judge":"MRS PAULA HARTINGER (175)","Number":4,"Count":2,"BreedName":"Brussels Griffons ","DogCount":0,"BitchCount":0,"SpecialDogCount":1,"SpecialBitchCount":1,"CountAhead":11},{"BlockStart":"12:40 pm","Judge":"MRS PAULA HARTINGER (175)","Number":4,"Count":2,"BreedName":"Shih Tzu ","DogCount":0,"BitchCount":1,"SpecialDogCount":0,"SpecialBitchCount":1,"CountAhead":13},{"BlockStart":"12:40 pm","Judge":"MRS PAULA HARTINGER (175)","Number":4,"Count":17,"BreedName":"Chinese Cresteds ","DogCount":4,"BitchCount":9,"SpecialDogCount":2,"SpecialBitchCount":2,"CountAhead":15},{"BlockStart":"12:40 pm","Judge":"MRS PAULA HARTINGER (175)","Number":4,"Count":1,"BreedName":"Maltese ","DogCount":0,"BitchCount":0,"SpecialDogCount":1,"SpecialBitchCount":0,"CountAhead":32},{"BlockStart":"12:40 pm","Judge":"MRS PAULA HARTINGER (175)","Number":4,"Count":19,"BreedName":"Pomeranians ","DogCount":7,"BitchCount":8,"SpecialDogCount":3,"SpecialBitchCount":1,"CountAhead":33},{"BlockStart":"12:40 pm","Judge":"MRS PAULA HARTINGER (175)","Number":4,"Count":10,"BreedName":"Havanese ","DogCount":2,"BitchCount":6,"SpecialDogCount":1,"SpecialBitchCount":1,"CountAhead":52},{"Empty":"obedience: not captured","BlockStart":"8:00 am","Judge":"MRS ANNA LORENZ (15)","Number":5},{"Empty":"obedience: not captured","BlockStart":"8:20 am","Judge":"MRS ANNA LORENZ (15)","Number":5},{"Empty":"obedience: not captured","BlockStart":"9:00 am","Judge":"MRS ANNA LORENZ (15)","Number":5},{"Empty":"obedience: not captured","BlockStart":"9:15 am","Judge":"MRS ANNA LORENZ (15)","Number":5},{"Empty":"obedience: not captured","BlockStart":"10:00 am","Judge":"MR CHARLES W KLINE (11)","Number":5},{"Empty":"obedience: not captured","BlockStart":"10:40 am","Judge":"MR CHARLES W KLINE (11)","Number":5},{"Empty":"obedience: not captured","BlockStart":"11:00 am","Judge":"MR CHARLES W KLINE (11)","Number":5},{"Empty":"rally: not captured","BlockStart":"12:00 pm","Judge":"MR CHARLES W KLINE (20)","Number":5},{"Empty":"rally: not captured","BlockStart":"12:10 pm","Judge":"MR CHARLES W KLINE (20)","Number":5},{"Empty":"rally: not captured","BlockStart":"12:10 pm","Judge":"MR CHARLES W KLINE (20)","Number":5},{"Empty":"rally: not captured","BlockStart":"12:10 pm","Judge":"MR CHARLES W KLINE (20)","Number":5},{"Empty":"rally: not captured","BlockStart":"12:10 pm","Judge":"MR CHARLES W KLINE (20)","Number":5},{"Empty":"rally: not captured","BlockStart":"12:10 pm","Judge":"MR CHARLES W KLINE (20)","Number":5},{"Empty":"rally: not captured","BlockStart":"12:10 pm","Judge":"MR CHARLES W KLINE (20)","Number":5},{"Empty":"rally: not captured","BlockStart":"12:10 pm","Judge":"MR CHARLES W KLINE (20)","Number":5},{"Empty":"rally: not captured","BlockStart":"12:10 pm","Judge":"MR CHARLES W KLINE (20)","Number":5},{"Group":"SPORTING GROUP","Judge":"DR BOB G SMITH","Time":"1:30 pm"},{"Group":"HERDING GROUP","Judge":"MR ROGER R HARTINGER","Time":"1:30 pm"},{"Group":"NON-SPORTING GROUP","Judge":"MR ROGER R HARTINGER","Time":"1:30 pm"},{"Group":"HOUND GROUP","Judge":"MRS PAULA HARTINGER","Time":"1:30 pm"},{"Group":"WORKING GROUP","Judge":"MRS PAULA HARTINGER","Time":"1:30 pm"},{"Group":"TERRIER GROUP","Judge":"MR ROGER R HARTINGER","Time":"1:30 pm"},{"Group":"TOY GROUP","Judge":"MR JASON HOKE","Time":"1:30 pm"},{"Group":"BEST IN SHOW","Judge":"DR EDNA K MARTIN","Time":"1:30 pm"}]}